{
    "picUrls": [
        "asset/image/avatar/官方人物素材2/独角兽.png"
    ],
    "oriMode": 4,
    "refObjs": {},
    "parts": [
        {
            "id": 0,
            "showOnEditor": true,
            "mouseEventEnabledInEditor": true
        }
    ],
    "actionListArr": [
        {
            "id": 1,
            "frameImageInfo": [
                [
                    {
                        "picUrlIndex": 0,
                        "rect": [
                            0,
                            0,
                            69,
                            96
                        ],
                        "x": -34.5,
                        "y": -96,
                        "width": 69,
                        "height": 96,
                        "rotation": 0,
                        "alpha": 1
                    }
                ],
                [
                    {
                        "picUrlIndex": 0,
                        "rect": [
                            0,
                            -96,
                            69,
                            96
                        ],
                        "x": -34.5,
                        "y": -96,
                        "width": 69,
                        "height": 96,
                        "rotation": 0,
                        "alpha": 1
                    }
                ],
                [
                    {
                        "picUrlIndex": 0,
                        "rect": [
                            0,
                            -192,
                            69,
                            96
                        ],
                        "x": -34.5,
                        "y": -96,
                        "width": 69,
                        "height": 96,
                        "rotation": 0,
                        "alpha": 1
                    }
                ],
                [
                    {
                        "picUrlIndex": 0,
                        "rect": [
                            0,
                            -288,
                            69,
                            96
                        ],
                        "x": -34.5,
                        "y": -96,
                        "width": 69,
                        "height": 96,
                        "rotation": 0,
                        "alpha": 1
                    }
                ]
            ]
        },
        {
            "id": 2,
            "frameImageInfo": [
                [
                    {
                        "picUrlIndex": 0,
                        "rect": [
                            0,
                            0,
                            69,
                            96
                        ],
                        "x": -34.5,
                        "y": -96,
                        "width": 69,
                        "height": 96,
                        "rotation": 0,
                        "alpha": 1
                    },
                    {
                        "picUrlIndex": 0,
                        "rect": [
                            -69,
                            0,
                            69,
                            96
                        ],
                        "x": -34.5,
                        "y": -96,
                        "width": 69,
                        "height": 96,
                        "rotation": 0,
                        "alpha": 1
                    },
                    {
                        "picUrlIndex": 0,
                        "rect": [
                            -138,
                            0,
                            69,
                            96
                        ],
                        "x": -34.5,
                        "y": -96,
                        "width": 69,
                        "height": 96,
                        "rotation": 0,
                        "alpha": 1
                    },
                    {
                        "picUrlIndex": 0,
                        "rect": [
                            -207,
                            0,
                            69,
                            96
                        ],
                        "x": -34.5,
                        "y": -96,
                        "width": 69,
                        "height": 96,
                        "rotation": 0,
                        "alpha": 1
                    }
                ],
                [
                    {
                        "picUrlIndex": 0,
                        "rect": [
                            0,
                            -96,
                            69,
                            96
                        ],
                        "x": -34.5,
                        "y": -96,
                        "width": 69,
                        "height": 96,
                        "rotation": 0,
                        "alpha": 1
                    },
                    {
                        "picUrlIndex": 0,
                        "rect": [
                            -69,
                            -96,
                            69,
                            96
                        ],
                        "x": -34.5,
                        "y": -96,
                        "width": 69,
                        "height": 96,
                        "rotation": 0,
                        "alpha": 1
                    },
                    {
                        "picUrlIndex": 0,
                        "rect": [
                            -138,
                            -96,
                            69,
                            96
                        ],
                        "x": -34.5,
                        "y": -96,
                        "width": 69,
                        "height": 96,
                        "rotation": 0,
                        "alpha": 1
                    },
                    {
                        "picUrlIndex": 0,
                        "rect": [
                            -207,
                            -96,
                            69,
                            96
                        ],
                        "x": -34.5,
                        "y": -96,
                        "width": 69,
                        "height": 96,
                        "rotation": 0,
                        "alpha": 1
                    }
                ],
                [
                    {
                        "picUrlIndex": 0,
                        "rect": [
                            0,
                            -192,
                            69,
                            96
                        ],
                        "x": -34.5,
                        "y": -96,
                        "width": 69,
                        "height": 96,
                        "rotation": 0,
                        "alpha": 1
                    },
                    {
                        "picUrlIndex": 0,
                        "rect": [
                            -69,
                            -192,
                            69,
                            96
                        ],
                        "x": -34.5,
                        "y": -96,
                        "width": 69,
                        "height": 96,
                        "rotation": 0,
                        "alpha": 1
                    },
                    {
                        "picUrlIndex": 0,
                        "rect": [
                            -138,
                            -192,
                            69,
                            96
                        ],
                        "x": -34.5,
                        "y": -96,
                        "width": 69,
                        "height": 96,
                        "rotation": 0,
                        "alpha": 1
                    },
                    {
                        "picUrlIndex": 0,
                        "rect": [
                            -207,
                            -192,
                            69,
                            96
                        ],
                        "x": -34.5,
                        "y": -96,
                        "width": 69,
                        "height": 96,
                        "rotation": 0,
                        "alpha": 1
                    }
                ],
                [
                    {
                        "picUrlIndex": 0,
                        "rect": [
                            0,
                            -288,
                            69,
                            96
                        ],
                        "x": -34.5,
                        "y": -96,
                        "width": 69,
                        "height": 96,
                        "rotation": 0,
                        "alpha": 1
                    },
                    {
                        "picUrlIndex": 0,
                        "rect": [
                            -69,
                            -288,
                            69,
                            96
                        ],
                        "x": -34.5,
                        "y": -96,
                        "width": 69,
                        "height": 96,
                        "rotation": 0,
                        "alpha": 1
                    },
                    {
                        "picUrlIndex": 0,
                        "rect": [
                            -138,
                            -288,
                            69,
                            96
                        ],
                        "x": -34.5,
                        "y": -96,
                        "width": 69,
                        "height": 96,
                        "rotation": 0,
                        "alpha": 1
                    },
                    {
                        "picUrlIndex": 0,
                        "rect": [
                            -207,
                            -288,
                            69,
                            96
                        ],
                        "x": -34.5,
                        "y": -96,
                        "width": 69,
                        "height": 96,
                        "rotation": 0,
                        "alpha": 1
                    }
                ]
            ]
        }
    ],
    "id": 1018
}